myosutils.py
myosutils-1.0.0.dist-info/LICENSE
myosutils-1.0.0.dist-info/METADATA
myosutils-1.0.0.dist-info/WHEEL
myosutils-1.0.0.dist-info/top_level.txt
myosutils-1.0.0.dist-info/RECORD
