Metadata-Version: 2.1
Name: myosutils
Version: 1.0.0
Summary: OS Utils Library
Home-page: https://github.com/governorbaloyi/pypi-myosutils
Author: Governor Baloyi
Author-email: governor.baloyi@gmail.com
License: UNKNOWN
Platform: UNKNOWN
Classifier: Development Status :: 1 - Planning
Classifier: Framework :: Pytest
Classifier: License :: OSI Approved :: MIT License
Classifier: Programming Language :: Python :: 3 :: Only
Provides-Extra: dev
Requires-Dist: pytest (>=3.7) ; extra == 'dev'
